quantio/__init__.py
quantio/exceptions.py
quantio/quantities.py
quantio/vector.py
quantio-0.19.2.dist-info/LICENSE
quantio-0.19.2.dist-info/METADATA
quantio-0.19.2.dist-info/WHEEL
quantio-0.19.2.dist-info/RECORD
