Metadata-Version: 2.1
Name: quantio
Version: 0.19.2
Summary: Type hinting and safe unit conversion for physical quantities in Python.
Home-page: https://github.com/unexcellent/quantio
Requires-Python: >=3.10,<3.14
Classifier: Programming Language :: Python :: 3
Classifier: Programming Language :: Python :: 3.10
Classifier: Programming Language :: Python :: 3.11
Classifier: Programming Language :: Python :: 3.12
Classifier: Programming Language :: Python :: 3.13
Requires-Dist: numpy (>=2.1.3,<3.0.0)
Project-URL: Repository, https://github.com/unexcellent/quantio
